libovsdb
