Metadata-Version: 1.0
Name: libovsdb
Version: 1.0.13
Summary: An OVSDB Library written in python.
Home-page: https://github.com/guoyoooping/libovsdb
Author: Yongping Guo
Author-email: guoyoooping@163.com
License: GPLv3
Platform: UNKNOWN
